OurCrypt/Script.py
OurCrypt/__init__.py
ourcrypt-0.0.1.dist-info/METADATA
ourcrypt-0.0.1.dist-info/WHEEL
ourcrypt-0.0.1.dist-info/licenses/LICENSE
ourcrypt-0.0.1.dist-info/RECORD
